setup.py
bin/pyrpncalc
pyrpncalc/__init__.py
pyrpncalc/__main__.py
pyrpncalc.egg-info/PKG-INFO
pyrpncalc.egg-info/SOURCES.txt
pyrpncalc.egg-info/dependency_links.txt
pyrpncalc.egg-info/top_level.txt
pyrpncalc.egg-info/zip-safe